wiremind_kubernetes/__init__.py
wiremind_kubernetes/exceptions.py
wiremind_kubernetes/kube_config.py
wiremind_kubernetes/kubernetes_client_additional_arguments.py
wiremind_kubernetes/kubernetes_helper.py
wiremind_kubernetes/py.typed
wiremind_kubernetes/utils.py
wiremind_kubernetes/tests/__init__.py
wiremind_kubernetes/tests/e2e_tests/__init__.py
wiremind_kubernetes/tests/e2e_tests/conftest.py
wiremind_kubernetes/tests/e2e_tests/create_job_test.py
wiremind_kubernetes/tests/e2e_tests/helpers.py
wiremind_kubernetes/tests/e2e_tests/start_stop_test.py
wiremind_kubernetes/tests/unit_tests/__init__.py
wiremind_kubernetes/tests/unit_tests/kube_config_test.py
wiremind_kubernetes/tests/unit_tests/kubernetes_client_additional_arguments_test.py
wiremind_kubernetes/tests/unit_tests/kubernetes_deployment_manager_test.py
wiremind_kubernetes/tests/unit_tests/namespaced_kubernetes_helper_test.py
wiremind_kubernetes/tests/unit_tests/utils_test/__init__.py
wiremind_kubernetes/tests/unit_tests/utils_test/retry_kubernetes_request_test.py
wiremind_kubernetes/tests/unit_tests/utils_test/run_command_test.py
wiremind_kubernetes-7.5.0.dist-info/LICENCE.md
wiremind_kubernetes-7.5.0.dist-info/METADATA
wiremind_kubernetes-7.5.0.dist-info/WHEEL
wiremind_kubernetes-7.5.0.dist-info/top_level.txt
wiremind_kubernetes-7.5.0.dist-info/zip-safe
wiremind_kubernetes-7.5.0.dist-info/RECORD
