Metadata-Version: 2.2
Name: wiremind-kubernetes
Version: 7.5.0
Summary: Helper for Kubernetes.
Home-page: https://github.com/wiremind/wiremind-kubernetes
Author: Wiremind
Author-email: dev@wiremind.io
License: LGPLv3+
Keywords: kubernetes
Classifier: Development Status :: 5 - Production/Stable
Classifier: Intended Audience :: Developers
Classifier: License :: OSI Approved :: GNU Lesser General Public License v3 or later (LGPLv3+)
Requires-Python: >=3.9.0
License-File: LICENCE.md
Requires-Dist: kubernetes>=18.0.0
Provides-Extra: dev
Requires-Dist: flake8; extra == "dev"
Requires-Dist: black; extra == "dev"
Requires-Dist: isort; extra == "dev"
Requires-Dist: bandit; extra == "dev"
Requires-Dist: flake8-mutable; extra == "dev"
Requires-Dist: pip-tools>=3.7.0; extra == "dev"
Requires-Dist: pyupgrade; extra == "dev"
Requires-Dist: safety; extra == "dev"
Requires-Dist: mypy; extra == "dev"
Requires-Dist: mock; extra == "dev"
Requires-Dist: pytest; extra == "dev"
Requires-Dist: pytest-mock; extra == "dev"
Provides-Extra: mypy
Requires-Dist: mypy; extra == "mypy"
Provides-Extra: test
Requires-Dist: mock; extra == "test"
Requires-Dist: pytest; extra == "test"
Requires-Dist: pytest-mock; extra == "test"
Dynamic: author
Dynamic: author-email
Dynamic: classifier
Dynamic: description
Dynamic: home-page
Dynamic: keywords
Dynamic: license
Dynamic: provides-extra
Dynamic: requires-dist
Dynamic: requires-python
Dynamic: summary
